{
  "content": [
    {
      "content": null,
      "created": "2023-05-14T01:12:30.760804Z",
      "format": null,
      "last_modified": "2023-05-14T01:12:05.808175Z",
      "mimetype": null,
      "name": "data-science-python-plotting.ipynb",
      "path": "data-science-python-plotting.ipynb",
      "size": 140762,
      "type": "notebook",
      "writable": true
    },
    {
      "content": null,
      "created": "2023-05-14T01:12:30.756804Z",
      "format": null,
      "last_modified": "2023-05-14T01:12:05.808175Z",
      "mimetype": null,
      "name": "data-science-python-basics.ipynb",
      "path": "data-science-python-basics.ipynb",
      "size": 150671,
      "type": "notebook",
      "writable": true
    },
    {
      "content": null,
      "created": "2023-05-14T01:12:30.756804Z",
      "format": null,
      "last_modified": "2023-05-14T01:12:05.804175Z",
      "mimetype": null,
      "name": "data-science-python-advanced-np-pd.ipynb",
      "path": "data-science-python-advanced-np-pd.ipynb",
      "size": 110763,
      "type": "notebook",
      "writable": true
    }
  ],
  "created": "2023-05-14T01:12:30.760804Z",
  "format": "json",
  "last_modified": "2023-05-14T01:12:30.760804Z",
  "mimetype": null,
  "name": "",
  "path": "",
  "size": null,
  "type": "directory",
  "writable": true
}